AUTHORS.rst
CONTRIBUTING.rst
HISTORY.rst
LICENSE
MANIFEST.in
Makefile
README.rst
setup.cfg
setup.py
docs/Makefile
docs/authors.rst
docs/conf.py
docs/contributing.rst
docs/history.rst
docs/index.rst
docs/make.bat
docs/readme.rst
docs/usage.rst
tests/__init__.py
tests/test_webobentrypoints.py
webobentrypoints/__init__.py
webobentrypoints.egg-info/PKG-INFO
webobentrypoints.egg-info/SOURCES.txt
webobentrypoints.egg-info/dependency_links.txt
webobentrypoints.egg-info/entry_points.txt
webobentrypoints.egg-info/not-zip-safe
webobentrypoints.egg-info/requires.txt
webobentrypoints.egg-info/top_level.txt