Metadata-Version: 1.1
Name: webobentrypoints
Version: 0.1.0
Summary: PasteDeploy entry points for WebOb WSGI apps and filters.
Home-page: https://github.com/regebro/webobentrypoints
Author: Lennart Regebro
Author-email: regebro@gmail.com
License: BSD
Keywords: webobentrypoints
Platform: UNKNOWN
Classifier: Development Status :: 3 - Alpha
Classifier: Intended Audience :: Developers
Classifier: License :: OSI Approved :: MIT License
Classifier: Natural Language :: English
Classifier: Programming Language :: Python :: 2
Classifier: Programming Language :: Python :: 2.6
Classifier: Programming Language :: Python :: 2.7
Classifier: Programming Language :: Python :: 3
Classifier: Programming Language :: Python :: 3.3
Classifier: Programming Language :: Python :: 3.4
